mockseries/__init__.py
mockseries/__main__.py
mockseries/main.py
mockseries/interaction/__init__.py
mockseries/interaction/additive_interaction.py
mockseries/interaction/interaction.py
mockseries/interaction/multiplicative_interaction.py
mockseries/noise/__init__.py
mockseries/noise/gaussian_noise.py
mockseries/noise/noise.py
mockseries/noise/red_noise.py
mockseries/seasonality/__init__.py
mockseries/seasonality/daily_seasonality.py
mockseries/seasonality/period_seasonality.py
mockseries/seasonality/seasonality.py
mockseries/seasonality/sinusoidal_seasonality.py
mockseries/seasonality/weekly_seasonality.py
mockseries/seasonality/yearly_seasonality.py
mockseries/signal/__init__.py
mockseries/signal/composed_signal.py
mockseries/signal/signal.py
mockseries/transition/__init__.py
mockseries/transition/direct_transition.py
mockseries/transition/lambda_transition.py
mockseries/transition/linear_transition.py
mockseries/transition/transition.py
mockseries/trend/__init__.py
mockseries/trend/exponential_trend.py
mockseries/trend/flat_trend.py
mockseries/trend/linear_trend.py
mockseries/trend/switch.py
mockseries/utils/__init__.py
mockseries/utils/dates.py
mockseries/utils/plot.py
mockseries/utils/timedeltas.py
mockseries/utils/writers.py
mockseries-0.3.1.dist-info/LICENSE
mockseries-0.3.1.dist-info/METADATA
mockseries-0.3.1.dist-info/WHEEL
mockseries-0.3.1.dist-info/entry_points.txt
mockseries-0.3.1.dist-info/top_level.txt
mockseries-0.3.1.dist-info/RECORD
