Metadata-Version: 2.1
Name: mockseries
Version: 0.3.1
Summary: Easy and intuitive generation of synthetic timeseries.
Home-page: http://mockseries.catheu.tech/
Author: Cyril de Catheu
Author-email: cdecatheu@hey.com
License: BSD
Project-URL: Bug Tracker, https://github.com/cyrilou242/mockseries/issues
Project-URL: Documentation, http://mockseries.catheu.tech/
Project-URL: Source Code, https://github.com/cyrilou242/mockseries
Platform: UNKNOWN
Classifier: Intended Audience :: Science/Research
Classifier: Intended Audience :: Developers
Classifier: License :: OSI Approved :: BSD License
Classifier: Programming Language :: Python
Classifier: Programming Language :: Python :: 3
Classifier: Programming Language :: Python :: 3.9
Classifier: Programming Language :: Python :: 3.10
Classifier: Programming Language :: Python :: 3.11
Classifier: Programming Language :: Python :: 3.12
Classifier: Programming Language :: Python :: 3 :: Only
Classifier: Topic :: Software Development
Classifier: Topic :: Scientific/Engineering
Classifier: Typing :: Typed
Classifier: Operating System :: OS Independent
Classifier: Operating System :: Microsoft :: Windows
Classifier: Operating System :: POSIX
Classifier: Operating System :: Unix
Classifier: Operating System :: MacOS
Requires-Python: >=3.9,<3.13
License-File: LICENSE
Requires-Dist: matplotlib ==3.7.1
Requires-Dist: numpy ==1.26.3
Requires-Dist: scipy ==1.11.4
